jshdate/__init__.py
jshdate-0.3.0.dist-info/METADATA
jshdate-0.3.0.dist-info/WHEEL
jshdate-0.3.0.dist-info/top_level.txt
jshdate-0.3.0.dist-info/RECORD
